gan_face_generate/__init__.py
gan_face_generate/dataset.py
gan_face_generate/inference.py
gan_face_generate/models.py
gan_face_generate/train.py
gan_face_generate/weights.tar
gan_face_generate-1.1.1.dist-info/licenses/LICENSE
gan_face_generate-1.1.1.dist-info/METADATA
gan_face_generate-1.1.1.dist-info/WHEEL
gan_face_generate-1.1.1.dist-info/entry_points.txt
gan_face_generate-1.1.1.dist-info/top_level.txt
gan_face_generate-1.1.1.dist-info/RECORD
