Metadata-Version: 2.4
Name: gan_face_generate
Version: 1.1.1
Summary: Generate a random face created by DCGAN trained with DigiFace1M database
Author-email: Chien Liu <chienliu6001@gmail.com>
License: Copyright (c) 2023, chien liu
Project-URL: Homepage, https://github.com/chien-liu/DCGAN-PyTorch
Classifier: License :: OSI Approved :: MIT License
Classifier: Programming Language :: Python
Classifier: Programming Language :: Python :: 3
Classifier: Programming Language :: Python :: 3 :: Only
Requires-Python: <3.13,>=3.10
License-File: LICENSE
Requires-Dist: matplotlib>=3.8.0
Requires-Dist: numpy>=1.26.0
Requires-Dist: platformdirs>=4.3.8
Requires-Dist: requests>=2.32.4
Requires-Dist: torch>=2.1.0
Requires-Dist: torchvision>=0.16.0
Requires-Dist: tqdm>=4.67.1
Requires-Dist: wandb[media]>=0.20.1
Provides-Extra: dev
Requires-Dist: mypy==1.16.1; extra == "dev"
Requires-Dist: pandas-stubs>=2.0.0; extra == "dev"
Requires-Dist: pre-commit>=3.0.0; extra == "dev"
Requires-Dist: pytest>=8.4.1; extra == "dev"
Requires-Dist: ruff==0.12.1; extra == "dev"
Requires-Dist: types-requests>=2.32; extra == "dev"
Dynamic: license-file
